[
    {
      "address": "0xEBee77c003BF88aC7D3C694086594E445098Ce85",
      "flightNumber": "UA131",
      "airline": "United Airlines",
      "origin": "EWR",
      "destination": "HND",
      "departureTime": "Mar 1, 2023 13:20 EST",
      "status": "Unknown"
    },
    {
      "address": "0xEBee77c003BF88aC7D3C694086594E445098Ce85",
      "flightNumber": "UA2010",
      "airline": "United Airlines",
      "origin": "EWR",
      "destination": "SFO",
      "departureTime": "Mar 1, 2023 14:10 EST",
      "status": "Unknown"
    },
    {
      "address": "0xEBee77c003BF88aC7D3C694086594E445098Ce85",
      "flightNumber": "DL487",
      "airline": "Delta Airlines",
      "origin": "JFK",
      "destination": "SFO",
      "departureTime": "Mar 1, 2023 14:10 EST",
      "status": "Unknown"
    },
    {
      "address": "0xEBee77c003BF88aC7D3C694086594E445098Ce85",
      "flightNumber": "DL312",
      "airline": "Delta Airlines",
      "origin": "JFK",
      "destination": "HNL",
      "departureTime": "Mar 1, 2023 9:00 EST",
      "status": "Unknown"
    },
    {
      "address": "0xEBee77c003BF88aC7D3C694086594E445098Ce85",
      "flightNumber": "DL5996",
      "airline": "Delta Airlines",
      "origin": "JFK",
      "destination": "LHR",
      "departureTime": "Mar 1, 2023 8:15 EST",
      "status": "Unknown"
    },
    {
      "address": "0xEBee77c003BF88aC7D3C694086594E445098Ce85",
      "flightNumber": "DL272",
      "airline": "Delta Airlines",
      "origin": "JFK",
      "destination": "LIS",
      "departureTime": "Mar 1, 2023 20:00 EST",
      "status": "Unknown"
    }]